RecarrayTools/AppendFields.py
RecarrayTools/AssignToRecarray.py
RecarrayTools/InterpRecarrayFields.py
RecarrayTools/JoinRecarray.py
RecarrayTools/ProgressBar.py
RecarrayTools/ReadRecarray.py
RecarrayTools/ReduceRecarray.py
RecarrayTools/SaveRecarray.py
RecarrayTools/_InterpGaps.py
RecarrayTools/_ReadDtype.py
RecarrayTools/_StoreDtype.py
RecarrayTools/__init__.py
RecarrayTools-0.1.1.dist-info/LICENSE
RecarrayTools-0.1.1.dist-info/METADATA
RecarrayTools-0.1.1.dist-info/WHEEL
RecarrayTools-0.1.1.dist-info/top_level.txt
RecarrayTools-0.1.1.dist-info/RECORD
