Metadata-Version: 2.1
Name: RecarrayTools
Version: 0.1.1
Summary: Some simple tools for managing numpy.recarray objects
Home-page: https://github.com/mattkjames7/RecarrayTools
Author: Matthew Knight James
Author-email: mattkjames7@gmail.com
License: UNKNOWN
Platform: UNKNOWN
Classifier: Programming Language :: Python :: 3
Classifier: License :: OSI Approved :: MIT License
Classifier: Operating System :: POSIX
Requires-Dist: numpy
Requires-Dist: scipy
